azkaban/__init__.py
azkaban/__main__.py
azkaban/job.py
azkaban/project.py
azkaban/remote.py
azkaban/util.py
azkaban/ext/__init__.py
azkaban/ext/flow.py
azkaban/ext/pig.py
azkaban-0.9.8.dist-info/AUTHORS
azkaban-0.9.8.dist-info/LICENSE
azkaban-0.9.8.dist-info/METADATA
azkaban-0.9.8.dist-info/WHEEL
azkaban-0.9.8.dist-info/entry_points.txt
azkaban-0.9.8.dist-info/top_level.txt
azkaban-0.9.8.dist-info/RECORD
