Metadata-Version: 2.1
Name: azkaban
Version: 0.9.8
Summary: AzkabanCLI: a lightweight command line interface for Azkaban.
Home-page: http://azkabancli.readthedocs.org/
Author: Matthieu Monsch
Author-email: monsch@alum.mit.edu
License: MIT
Platform: UNKNOWN
Classifier: Development Status :: 4 - Beta
Classifier: Intended Audience :: Developers
Classifier: License :: OSI Approved :: MIT License
Classifier: Programming Language :: Python
Classifier: Programming Language :: Python :: 2.6
Classifier: Programming Language :: Python :: 2.7
Classifier: Programming Language :: Python :: 3
Classifier: Programming Language :: Python :: 3.3
Requires-Dist: six (>=1.6.1)
Requires-Dist: docopt
Requires-Dist: requests (>=2.4.0)
Requires-Dist: urllib3
